djangrpc/__init__.py
djangrpc-0.0.1.dist-info/METADATA
djangrpc-0.0.1.dist-info/WHEEL
djangrpc-0.0.1.dist-info/top_level.txt
djangrpc-0.0.1.dist-info/RECORD
