Metadata-Version: 2.1
Name: djangrpc
Version: 0.0.1
Summary: Django + Grpc. The Grpc web framework for perfectionists with deadlines.
Home-page: https://github.com/zaihui/djangrpc
Author: Lirian Su
Author-email: liriansu@gmail.com
License: MIT License
Platform: UNKNOWN
Requires-Dist: django (>=3.0.0)
Requires-Dist: elastic-apm (>=5.6.0)
Requires-Dist: grpcio (>=1.29.0)
Requires-Dist: grpcio-health-checking (>=1.29.0)
Requires-Dist: hutils (>=1.0.7)
Requires-Dist: protobuf (==3.11.3)
Requires-Dist: pymysql (>=0.9.3)
Requires-Dist: sentry-sdk (>=0.14.4)
